[
    {
        "name": "Quick Links",
        "links": [
            {
                "name": "Jobs at UNDP",
                "link": "https://www.undp.org/"
            },
            {
                "name": "Partnerships",
                "link": "https://www.undp.org/"
            },
            {
                "name": "Donate",
                "link": "https://www.undp.org/"
            }
        ]
    },
    {
        "name": "Popular Searches",
        "links": [
            {
                "name": "ODS",
                "link": "https://www.undp.org/"
            },
            {
                "name": "Sustainable Development Goals",
                "link": "https://www.undp.org/"
            },
            {
                "name": "COVID 19",
                "link": "https://www.undp.org/"
            }
        ]
    }
]
